# -==[ disX by namdevel ]==-
# URL : https://github.com/namdevel/disX
# File: src/_run.pyc (Python 3.10)

[Code]
    File Name: wait, you really thought lmao
    Object Name: <module>
    Arg Count: 0
    Pos Only Arg Count: 0
    KW Only Arg Count: 0
    Locals: 0
    Stack Size: 8
    Flags: 0x00000040 (CO_NOFREE)
    [Names]
        '_'
        'src.apollyon'
        'ImportError'
        'input'
        'exit'
        'script'
        'globals'
        'key'
        'execute'
    [Var Names]
    [Free Vars]
    [Cell Vars]
    [Constants]
        'what are you looking for? you skid'
        0
        (
            '*'
        )
        "This script needs Python3.9 and the 'apollyon.pyd' library in order to be executed!"
        '\xec\x84\xb3\xec\x84\xb5\xec\x84\xac\xec\x84\xb1\xec\x84\xb7\xec\x83\xac\xec\x83\xa6\xec\x84\x8d\xec\x83\xab\xec\x84\xb0\xec\x83\xa4\xec\x84\xb6\xec\x84\xb7\xec\x84\xb5\xec\x84\xac\xec\x84\xb1\xec\x84\xaa\xec\x83\xa4\xec\x84\xb2\xec\x84\xa5\xec\x84\xa9\xec\x84\xb8\xec\x84\xb6\xec\x84\xa6\xec\x83\xbd\xec\x84\xb7\xec\x84\xa8\xec\x84\xa7\xec\x83\xa4\xec\x84\xa5\xec\x84\xbc\xec\x83\xa4\xec\x84\x85\xec\x84\xb3\xec\x84\xb2\xec\x84\xaf\xec\x84\xaf\xec\x84\xbc\xec\x84\xb2\xec\x84\xb1\xec\x83\xb2\xec\x84\xb3\xec\x84\xbc\xec\x84\xa7\xec\x83\xb2\xec\x83\xa4\xec\x84\x8d\xec\x84\xa9\xec\x83\xa4\xec\x84\xbc\xec\x84\xb2\xec\x84\xb8\xec\x83\xa4\xec\x84\xa6\xec\x83\xbd\xec\x84\xb1\xec\x83\xa4\xec\x84\xb5\xec\x84\xa8\xec\x83\xbd\xec\x84\xa7\xec\x83\xa4\xec\x84\xb0\xec\x84\xa8\xec\x83\xb0\xec\x83\xa4\xec\x84\xbc\xec\x84\xb2\xec\x84\xb8\xec\x83\xa4\xec\x84\xb6\xec\x84\xb8\xec\x84\xa6\xec\x84\xa6\xec\x84\xa8\xec\x84\xb6\xec\x84\xb6\xec\x83\xa4\xec\x84\xa7\xec\x84\xa8\xec\x84\xb2\xec\x84\xa5\xec\x84\xa9\xec\x84\xb8\xec\x84\xb6\xec\x84\xa6\xec\x83\xbd\xec\x84\xb7\xec\x84\xa8\xec\x84\xa7\xec\x83\xa4\xec\x84\x85\xec\x84\xb3\xec\x84\xb2\xec\x84\xaf\xec\x84\xaf\xec\x84\xbc\xec\x84\xb2\xec\x84\xb1\xec\x83\xa4\xec\x84\xb2\xec\x84\xa5\xec\x84\xa9\xec\x84\xb8\xec\x84\xb6\xec\x84\xa6\xec\x83\xbd\xec\x84\xb7\xec\x84\xb2\xec\x84\xb5\xec\x83\xa6\xec\x83\xad'
        'script'
        'key=356356'
        "exec(__import__('apollyon').decode(script, key))"
        None
    [Disassembly]
        0       LOAD_CONST              0: 'what are you looking for? you skid'
        2       STORE_NAME              0: _
        4       SETUP_FINALLY           6 (to 18)
        6       LOAD_CONST              1: 0
        8       LOAD_CONST              2: ('*',)
        10      IMPORT_NAME             1: src.apollyon
        12      IMPORT_STAR             
        14      POP_BLOCK               
        16      JUMP_FORWARD            16 (to 50)
        18      DUP_TOP                 
        20      LOAD_NAME               2: ImportError
        22      JUMP_IF_NOT_EXC_MATCH   24
        24      POP_TOP                 
        26      POP_TOP                 
        28      POP_TOP                 
        30      LOAD_NAME               3: input
        32      LOAD_CONST              3: "This script needs Python3.9 and the 'apollyon.pyd' library in order to be executed!"
        34      CALL_FUNCTION           1
        36      POP_TOP                 
        38      LOAD_NAME               4: exit
        40      CALL_FUNCTION           0
        42      POP_TOP                 
        44      POP_EXCEPT              
        46      JUMP_FORWARD            1 (to 50)
        48      RERAISE                 0
        50      LOAD_CONST              4: '\xec\x84\xb3\xec\x84\xb5\xec\x84\xac\xec\x84\xb1\xec\x84\xb7\xec\x83\xac\xec\x83\xa6\xec\x84\x8d\xec\x83\xab\xec\x84\xb0\xec\x83\xa4\xec\x84\xb6\xec\x84\xb7\xec\x84\xb5\xec\x84\xac\xec\x84\xb1\xec\x84\xaa\xec\x83\xa4\xec\x84\xb2\xec\x84\xa5\xec\x84\xa9\xec\x84\xb8\xec\x84\xb6\xec\x84\xa6\xec\x83\xbd\xec\x84\xb7\xec\x84\xa8\xec\x84\xa7\xec\x83\xa4\xec\x84\xa5\xec\x84\xbc\xec\x83\xa4\xec\x84\x85\xec\x84\xb3\xec\x84\xb2\xec\x84\xaf\xec\x84\xaf\xec\x84\xbc\xec\x84\xb2\xec\x84\xb1\xec\x83\xb2\xec\x84\xb3\xec\x84\xbc\xec\x84\xa7\xec\x83\xb2\xec\x83\xa4\xec\x84\x8d\xec\x84\xa9\xec\x83\xa4\xec\x84\xbc\xec\x84\xb2\xec\x84\xb8\xec\x83\xa4\xec\x84\xa6\xec\x83\xbd\xec\x84\xb1\xec\x83\xa4\xec\x84\xb5\xec\x84\xa8\xec\x83\xbd\xec\x84\xa7\xec\x83\xa4\xec\x84\xb0\xec\x84\xa8\xec\x83\xb0\xec\x83\xa4\xec\x84\xbc\xec\x84\xb2\xec\x84\xb8\xec\x83\xa4\xec\x84\xb6\xec\x84\xb8\xec\x84\xa6\xec\x84\xa6\xec\x84\xa8\xec\x84\xb6\xec\x84\xb6\xec\x83\xa4\xec\x84\xa7\xec\x84\xa8\xec\x84\xb2\xec\x84\xa5\xec\x84\xa9\xec\x84\xb8\xec\x84\xb6\xec\x84\xa6\xec\x83\xbd\xec\x84\xb7\xec\x84\xa8\xec\x84\xa7\xec\x83\xa4\xec\x84\x85\xec\x84\xb3\xec\x84\xb2\xec\x84\xaf\xec\x84\xaf\xec\x84\xbc\xec\x84\xb2\xec\x84\xb1\xec\x83\xa4\xec\x84\xb2\xec\x84\xa5\xec\x84\xa9\xec\x84\xb8\xec\x84\xb6\xec\x84\xa6\xec\x83\xbd\xec\x84\xb7\xec\x84\xb2\xec\x84\xb5\xec\x83\xa6\xec\x83\xad'
        52      STORE_NAME              5: script
        54      LOAD_NAME               5: script
        56      LOAD_NAME               6: globals
        58      LOAD_CONST              5: 'script'
        60      STORE_SUBSCR            
        62      LOAD_CONST              6: 'key=356356'
        64      STORE_NAME              7: key
        66      LOAD_NAME               8: execute
        68      LOAD_CONST              7: "exec(__import__('apollyon').decode(script, key))"
        70      CALL_FUNCTION           1
        72      POP_TOP                 
        74      LOAD_CONST              8: None
        76      RETURN_VALUE            
